runpandas/__init__.py
runpandas/_testing.py
runpandas/_utils.py
runpandas/_version.py
runpandas/conftest.py
runpandas/exceptions.py
runpandas/reader.py
runpandas/datasets/__init__.py
runpandas/datasets/config.yaml
runpandas/datasets/schema.py
runpandas/datasets/utils.py
runpandas/io/__init__.py
runpandas/io/fit/__init__.py
runpandas/io/fit/_parser.py
runpandas/io/gpx/__init__.py
runpandas/io/gpx/_parser.py
runpandas/io/nikerun/__init__.py
runpandas/io/nikerun/_parser.py
runpandas/io/result/__init__.py
runpandas/io/result/_parser.py
runpandas/io/strava/__init__.py
runpandas/io/strava/_client.py
runpandas/io/strava/_parser.py
runpandas/io/tcx/__init__.py
runpandas/io/tcx/_parser.py
runpandas/tests/__init__.py
runpandas/tests/test_columns.py
runpandas/tests/test_fit_parser.py
runpandas/tests/test_frame.py
runpandas/tests/test_gpx_reader.py
runpandas/tests/test_metrics_acessors.py
runpandas/tests/test_moving_acessors.py
runpandas/tests/test_nikerun_parser.py
runpandas/tests/test_reader.py
runpandas/tests/test_results_parser.py
runpandas/tests/test_session.py
runpandas/tests/test_splits_acessors.py
runpandas/tests/test_strava_client.py
runpandas/tests/test_strava_parser.py
runpandas/tests/test_summary.py
runpandas/tests/test_tcx_reader.py
runpandas/tests/test_utils.py
runpandas/tests/test_utils_datasets.py
runpandas/tests/test_xml_utils.py
runpandas/types/__init__.py
runpandas/types/columns.py
runpandas/types/frame.py
runpandas/types/summary.py
runpandas/types/acessors/__init__.py
runpandas/types/acessors/metrics.py
runpandas/types/acessors/moving.py
runpandas/types/acessors/session.py
runpandas/types/acessors/splits.py
runpandas-0.6.0.dist-info/LICENSE
runpandas-0.6.0.dist-info/METADATA
runpandas-0.6.0.dist-info/WHEEL
runpandas-0.6.0.dist-info/top_level.txt
runpandas-0.6.0.dist-info/RECORD
