Metadata-Version: 2.1
Name: runpandas
Version: 0.6.0
Summary: Running Tracking Analysis
Home-page: https://github.com/corriporai/runpandas
Author: RunPandas contributors
Author-email: marcel@caraciolo.com.br
License: BSD
Requires-Python: >=3.6
License-File: LICENSE
Requires-Dist: pandas (>=1.0.5)
Requires-Dist: fitparse
Requires-Dist: stravalib (>=0.10.2)
Requires-Dist: haversine
Requires-Dist: pydantic
Requires-Dist: pyyaml
Requires-Dist: thefuzz
